gameforecaster/__init__.py
gameforecaster/predictor.py
GameForecaster-1.0.0.dist-info/LICENSE
GameForecaster-1.0.0.dist-info/METADATA
GameForecaster-1.0.0.dist-info/WHEEL
GameForecaster-1.0.0.dist-info/top_level.txt
GameForecaster-1.0.0.dist-info/RECORD
