Metadata-Version: 2.1
Name: GameForecaster
Version: 1.0.0
Summary: A library to predict the success of video games based on various features.
Home-page: https://github.com/AzizBahloul/GameForecaster.git
Author: Si Aziz Bahloul
Author-email: azizbahloul3@gmail.com
Keywords: game prediction success machine-learning
Classifier: Programming Language :: Python :: 3
Classifier: License :: OSI Approved :: MIT License
Classifier: Operating System :: OS Independent
Classifier: Intended Audience :: Developers
Classifier: Topic :: Software Development :: Libraries :: Python Modules
Requires-Python: >=3.6
License-File: LICENSE
Requires-Dist: numpy
Requires-Dist: pandas
Requires-Dist: scikit-learn
Requires-Dist: joblib
